reveal_slides/__init__.py
reveal_slides/frontend/build/asset-manifest.json
reveal_slides/frontend/build/bootstrap.min.css
reveal_slides/frontend/build/index.html
reveal_slides/frontend/build/plugin/symbol-per-slide-progress/symbol-per-slide-progress.css
reveal_slides/frontend/build/static/css/10.1f3244e3.chunk.css
reveal_slides/frontend/build/static/css/10.1f3244e3.chunk.css.map
reveal_slides/frontend/build/static/css/11.cb699f02.chunk.css
reveal_slides/frontend/build/static/css/11.cb699f02.chunk.css.map
reveal_slides/frontend/build/static/css/12.158b51eb.chunk.css
reveal_slides/frontend/build/static/css/12.158b51eb.chunk.css.map
reveal_slides/frontend/build/static/css/13.74908590.chunk.css
reveal_slides/frontend/build/static/css/13.74908590.chunk.css.map
reveal_slides/frontend/build/static/css/14.e64fc659.chunk.css
reveal_slides/frontend/build/static/css/14.e64fc659.chunk.css.map
reveal_slides/frontend/build/static/css/15.3adba626.chunk.css
reveal_slides/frontend/build/static/css/15.3adba626.chunk.css.map
reveal_slides/frontend/build/static/css/16.b573d318.chunk.css
reveal_slides/frontend/build/static/css/16.b573d318.chunk.css.map
reveal_slides/frontend/build/static/css/17.10a8300f.chunk.css
reveal_slides/frontend/build/static/css/17.10a8300f.chunk.css.map
reveal_slides/frontend/build/static/css/18.4eb3e38a.chunk.css
reveal_slides/frontend/build/static/css/18.4eb3e38a.chunk.css.map
reveal_slides/frontend/build/static/css/19.74b97645.chunk.css
reveal_slides/frontend/build/static/css/19.74b97645.chunk.css.map
reveal_slides/frontend/build/static/css/2.5029ddca.chunk.css
reveal_slides/frontend/build/static/css/2.5029ddca.chunk.css.map
reveal_slides/frontend/build/static/css/3.2b87cc67.chunk.css
reveal_slides/frontend/build/static/css/3.2b87cc67.chunk.css.map
reveal_slides/frontend/build/static/css/4.3d16bc26.chunk.css
reveal_slides/frontend/build/static/css/4.3d16bc26.chunk.css.map
reveal_slides/frontend/build/static/css/5.5a2b8ee3.chunk.css
streamlit_reveal_slides-0.2.0.dist-info/LICENSE
streamlit_reveal_slides-0.2.0.dist-info/METADATA
streamlit_reveal_slides-0.2.0.dist-info/WHEEL
streamlit_reveal_slides-0.2.0.dist-info/top_level.txt
streamlit_reveal_slides-0.2.0.dist-info/RECORD
