Metadata-Version: 2.1
Name: streamlit-reveal-slides
Version: 0.2.0
Summary: reveal.js HTML presentations for streamlit
Home-page: https://github.com/bouzidanas/streamlit.io/tree/master/streamlit-reveal-slides
Author: Anas Bouzid
Author-email: 
Requires-Python: >=3.6
License-File: LICENSE
Requires-Dist: streamlit (>=0.63)
